{
  "openapi": "3.0.1",
  "info": {
    "title": "Backend",
    "version": "1.0"
  },
  "paths": {
    "/api/Categories/Create": {
      "post": {
        "tags": [
          "Categories"
        ],
        "requestBody": {
          "content": {
            "application/json": {
              "schema": {
                "$ref": "#/components/schemas/CreateCategoryDto"
              }
            },
            "text/json": {
              "schema": {
                "$ref": "#/components/schemas/CreateCategoryDto"
              }
            },
            "application/*+json": {
              "schema": {
                "$ref": "#/components/schemas/CreateCategoryDto"
              }
            }
          }
        },
        "responses": {
          "200": {
            "description": "OK"
          }
        }
      }
    },
    "/api/Categories": {
      "get": {
        "tags": [
          "Categories"
        ],
        "parameters": [
          {
            "name": "Serach",
            "in": "query",
            "schema": {
              "type": "string"
            }
          },
          {
            "name": "Page",
            "in": "query",
            "schema": {
              "type": "integer",
              "format": "int32"
            }
          },
          {
            "name": "PageSize",
            "in": "query",
            "schema": {
              "type": "integer",
              "format": "int32"
            }
          }
        ],
        "responses": {
          "200": {
            "description": "OK"
          }
        }
      }
    },
    "/api/Categories/{id}": {
      "get": {
        "tags": [
          "Categories"
        ],
        "parameters": [
          {
            "name": "id",
            "in": "path",
            "required": true,
            "schema": {
              "type": "integer",
              "format": "int32"
            }
          }
        ],
        "responses": {
          "200": {
            "description": "OK"
          }
        }
      }
    },
    "/api/Categories/Update/{id}": {
      "put": {
        "tags": [
          "Categories"
        ],
        "parameters": [
          {
            "name": "id",
            "in": "path",
            "required": true,
            "schema": {
              "type": "integer",
              "format": "int32"
            }
          }
        ],
        "requestBody": {
          "content": {
            "application/json": {
              "schema": {
                "$ref": "#/components/schemas/UpdateCategoryDto"
              }
            },
            "text/json": {
              "schema": {
                "$ref": "#/components/schemas/UpdateCategoryDto"
              }
            },
            "application/*+json": {
              "schema": {
                "$ref": "#/components/schemas/UpdateCategoryDto"
              }
            }
          }
        },
        "responses": {
          "200": {
            "description": "OK"
          }
        }
      }
    },
    "/api/Categories/Delete/{id}": {
      "delete": {
        "tags": [
          "Categories"
        ],
        "parameters": [
          {
            "name": "id",
            "in": "path",
            "required": true,
            "schema": {
              "type": "integer",
              "format": "int32"
            }
          }
        ],
        "responses": {
          "200": {
            "description": "OK"
          }
        }
      }
    },
    "/api/Categories/{id}/Items": {
      "get": {
        "tags": [
          "Categories"
        ],
        "parameters": [
          {
            "name": "id",
            "in": "path",
            "required": true,
            "schema": {
              "type": "integer",
              "format": "int32"
            }
          }
        ],
        "responses": {
          "200": {
            "description": "OK"
          }
        }
      }
    },
    "/api/Images/Upload": {
      "post": {
        "tags": [
          "Images"
        ],
        "requestBody": {
          "content": {
            "multipart/form-data": {
              "schema": {
                "type": "object",
                "properties": {
                  "Image": {
                    "type": "string",
                    "format": "binary"
                  },
                  "ItemId": {
                    "type": "integer",
                    "format": "int32"
                  }
                }
              },
              "encoding": {
                "Image": {
                  "style": "form"
                },
                "ItemId": {
                  "style": "form"
                }
              }
            }
          }
        },
        "responses": {
          "200": {
            "description": "OK"
          }
        }
      }
    },
    "/api/Items/Create": {
      "post": {
        "tags": [
          "Items"
        ],
        "requestBody": {
          "content": {
            "application/json": {
              "schema": {
                "$ref": "#/components/schemas/CreateItemDto"
              }
            },
            "text/json": {
              "schema": {
                "$ref": "#/components/schemas/CreateItemDto"
              }
            },
            "application/*+json": {
              "schema": {
                "$ref": "#/components/schemas/CreateItemDto"
              }
            }
          }
        },
        "responses": {
          "200": {
            "description": "OK"
          }
        }
      }
    },
    "/api/Items": {
      "get": {
        "tags": [
          "Items"
        ],
        "parameters": [
          {
            "name": "Serach",
            "in": "query",
            "schema": {
              "type": "string"
            }
          },
          {
            "name": "Page",
            "in": "query",
            "schema": {
              "type": "integer",
              "format": "int32"
            }
          },
          {
            "name": "PageSize",
            "in": "query",
            "schema": {
              "type": "integer",
              "format": "int32"
            }
          }
        ],
        "responses": {
          "200": {
            "description": "OK"
          }
        }
      }
    },
    "/api/Items/{id}": {
      "get": {
        "tags": [
          "Items"
        ],
        "parameters": [
          {
            "name": "id",
            "in": "path",
            "required": true,
            "schema": {
              "type": "integer",
              "format": "int32"
            }
          }
        ],
        "responses": {
          "200": {
            "description": "OK"
          }
        }
      }
    },
    "/api/Items/Update/{id}": {
      "put": {
        "tags": [
          "Items"
        ],
        "parameters": [
          {
            "name": "id",
            "in": "path",
            "required": true,
            "schema": {
              "type": "integer",
              "format": "int32"
            }
          }
        ],
        "requestBody": {
          "content": {
            "application/json": {
              "schema": {
                "$ref": "#/components/schemas/UpdateItemDto"
              }
            },
            "text/json": {
              "schema": {
                "$ref": "#/components/schemas/UpdateItemDto"
              }
            },
            "application/*+json": {
              "schema": {
                "$ref": "#/components/schemas/UpdateItemDto"
              }
            }
          }
        },
        "responses": {
          "200": {
            "description": "OK"
          }
        }
      }
    },
    "/api/Items/Delete/{id}": {
      "delete": {
        "tags": [
          "Items"
        ],
        "parameters": [
          {
            "name": "id",
            "in": "path",
            "required": true,
            "schema": {
              "type": "integer",
              "format": "int32"
            }
          }
        ],
        "responses": {
          "200": {
            "description": "OK"
          }
        }
      }
    },
    "/api/Items/{itemId}/image": {
      "get": {
        "tags": [
          "Items"
        ],
        "parameters": [
          {
            "name": "itemId",
            "in": "path",
            "required": true,
            "schema": {
              "type": "integer",
              "format": "int32"
            }
          }
        ],
        "responses": {
          "200": {
            "description": "OK"
          }
        }
      }
    }
  },
  "components": {
    "schemas": {
      "CreateCategoryDto": {
        "type": "object",
        "properties": {
          "name": {
            "type": "string",
            "nullable": true
          },
          "description": {
            "type": "string",
            "nullable": true
          }
        },
        "additionalProperties": false
      },
      "CreateItemDto": {
        "type": "object",
        "properties": {
          "name": {
            "type": "string",
            "nullable": true
          },
          "price": {
            "type": "number",
            "format": "double"
          },
          "categoryId": {
            "type": "integer",
            "format": "int32"
          }
        },
        "additionalProperties": false
      },
      "UpdateCategoryDto": {
        "type": "object",
        "properties": {
          "name": {
            "type": "string",
            "nullable": true
          },
          "description": {
            "type": "string",
            "nullable": true
          }
        },
        "additionalProperties": false
      },
      "UpdateItemDto": {
        "type": "object",
        "properties": {
          "name": {
            "type": "string",
            "nullable": true
          },
          "price": {
            "type": "number",
            "format": "double"
          },
          "categoryId": {
            "type": "integer",
            "format": "int32"
          }
        },
        "additionalProperties": false
      }
    }
  }
}